<?xml version="1.0"?>
<robot>
<canvas width="600" height="600">
</canvas>
<zoom x0="0.000000" y0="0.000000" x1="0.000000" y1="0.000000" x2="0.000000" y2="0.000000" x3="0.000000" y3="0.000000">
</zoom>/n<shapes>
<shape type="polyline" id="576" breakpoint="0" thickness="1"><color r="255" g="144" b="30"></color><points><p x="178" y="401"></p><p x="208" y="576"></p><p x="211" y="582"></p><p x="232" y="588"></p><p x="273" y="595"></p><p x="322" y="595"></p><p x="371" y="586"></p><p x="415" y="571"></p><p x="371" y="586"></p><p x="322" y="595"></p><p x="273" y="595"></p><p x="247" y="591"></p><p x="213" y="583"></p><p x="208" y="576"></p><p x="178" y="404"></p><p x="179" y="401"></p><p x="181" y="401"></p><p x="211" y="426"></p><p x="239" y="443"></p><p x="414" y="569"></p><p x="416" y="569"></p><p x="240" y="443"></p><p x="212" y="426"></p><p x="181" y="400"></p></points></shape>
<shape type="polyline" id="577" breakpoint="0" thickness="1"><color r="255" g="144" b="30"></color><points><p x="577" y="399"></p><p x="574" y="398"></p><p x="355" y="445"></p><p x="334" y="451"></p><p x="292" y="459"></p><p x="292" y="461"></p><p x="434" y="561"></p><p x="457" y="549"></p><p x="481" y="532"></p><p x="502" y="514"></p><p x="524" y="491"></p><p x="541" y="469"></p><p x="555" y="447"></p><p x="569" y="420"></p></points></shape>
<shape type="polyline" id="578" breakpoint="0" thickness="1"><color r="255" g="144" b="30"></color><points><p x="576" y="400"></p><p x="573" y="410"></p><p x="558" y="441"></p><p x="541" y="468"></p><p x="524" y="490"></p><p x="501" y="514"></p><p x="480" y="532"></p><p x="456" y="549"></p><p x="434" y="561"></p><p x="293" y="460"></p><p x="299" y="457"></p><p x="334" y="451"></p><p x="355" y="445"></p><p x="574" y="398"></p></points></shape>
<shape type="polyline" id="579" breakpoint="0" thickness="1"><color r="255" g="144" b="30"></color><points><p x="139" y="283"></p><p x="125" y="306"></p><p x="37" y="434"></p><p x="36" y="439"></p><p x="45" y="456"></p><p x="61" y="479"></p><p x="77" y="498"></p><p x="97" y="518"></p><p x="115" y="533"></p><p x="141" y="551"></p><p x="189" y="575"></p><p x="191" y="574"></p><p x="189" y="557"></p><p x="147" y="322"></p><p x="142" y="286"></p></points></shape>
<shape type="polyline" id="580" breakpoint="0" thickness="1"><color r="255" g="144" b="30"></color><points><p x="140" y="284"></p><p x="142" y="287"></p><p x="191" y="569"></p><p x="191" y="573"></p><p x="189" y="575"></p><p x="137" y="548"></p><p x="98" y="518"></p><p x="77" y="497"></p><p x="61" y="478"></p><p x="36" y="439"></p><p x="45" y="423"></p></points></shape>
<shape type="polyline" id="581" breakpoint="0" thickness="1"><color r="255" g="144" b="30"></color><points><p x="572" y="179"></p><p x="585" y="217"></p><p x="595" y="271"></p><p x="595" y="321"></p><p x="591" y="348"></p><p x="585" y="373"></p><p x="578" y="377"></p><p x="406" y="413"></p><p x="578" y="377"></p><p x="585" y="374"></p><p x="595" y="321"></p><p x="595" y="271"></p><p x="588" y="229"></p></points></shape>
<shape type="polyline" id="582" breakpoint="0" thickness="1"><color r="255" g="144" b="30"></color><points><p x="569" y="178"></p><p x="447" y="352"></p><p x="427" y="385"></p><p x="406" y="411"></p><p x="422" y="393"></p><p x="447" y="353"></p><p x="570" y="179"></p></points></shape>
<shape type="polyline" id="583" breakpoint="0" thickness="1"><color r="34" g="34" b="178"></color><points><p x="193" y="177"></p><p x="28" y="419"></p><p x="25" y="417"></p><p x="18" y="401"></p><p x="6" y="360"></p><p x="2" y="336"></p><p x="2" y="306"></p><p x="2" y="336"></p><p x="6" y="360"></p><p x="18" y="401"></p><p x="26" y="419"></p><p x="29" y="419"></p></points></shape>
<shape type="polyline" id="584" breakpoint="0" thickness="1"><color r="34" g="34" b="178"></color><points><p x="193" y="175"></p><p x="12" y="211"></p><p x="3" y="248"></p><p x="1" y="285"></p><p x="3" y="248"></p><p x="8" y="223"></p><p x="13" y="211"></p></points></shape>
<shape type="polyline" id="585" breakpoint="0" thickness="1"><color r="34" g="34" b="178"></color><points><p x="307" y="134"></p><p x="161" y="31"></p><p x="144" y="39"></p><p x="111" y="62"></p><p x="76" y="95"></p><p x="61" y="113"></p><p x="45" y="136"></p><p x="34" y="155"></p><p x="18" y="190"></p><p x="35" y="154"></p><p x="45" y="137"></p><p x="61" y="114"></p><p x="76" y="96"></p><p x="99" y="73"></p><p x="117" y="58"></p><p x="145" y="39"></p><p x="161" y="31"></p><p x="304" y="133"></p><p x="304" y="136"></p><p x="40" y="189"></p><p x="19" y="192"></p><p x="306" y="136"></p><p x="304" y="135"></p></points></shape>
<shape type="polyline" id="586" breakpoint="0" thickness="1"><color r="34" g="34" b="178"></color><points><p x="413" y="21"></p><p x="412" y="25"></p><p x="456" y="303"></p><p x="412" y="24"></p><p x="415" y="21"></p><p x="441" y="34"></p><p x="468" y="51"></p><p x="490" y="68"></p><p x="524" y="102"></p><p x="541" y="124"></p><p x="559" y="153"></p><p x="559" y="158"></p><p x="466" y="289"></p><p x="458" y="303"></p><p x="559" y="159"></p><p x="559" y="152"></p><p x="541" y="123"></p><p x="514" y="90"></p><p x="491" y="68"></p><p x="449" y="38"></p><p x="420" y="23"></p></points></shape>
<shape type="polyline" id="587" breakpoint="0" thickness="1"><color r="34" g="34" b="178"></color><points><p x="183" y="22"></p><p x="397" y="174"></p><p x="417" y="190"></p><p x="419" y="189"></p><p x="420" y="186"></p><p x="418" y="181"></p><p x="394" y="22"></p><p x="391" y="12"></p><p x="358" y="3"></p><p x="335" y="1"></p><p x="352" y="2"></p><p x="388" y="11"></p><p x="392" y="14"></p><p x="418" y="181"></p><p x="420" y="186"></p><p x="418" y="190"></p><p x="398" y="174"></p><p x="187" y="23"></p><p x="184" y="21"></p></points></shape>
</shapes>
</robot>
